{
  "palette": {
    "bright": {
      "background": {
        "value": "{colors.white}",
        "type": "color"
      },
      "shade": {
        "value": "{colors.silverMercury.500}",
        "type": "color"
      },
      "focus": {
        "outlineColor": {
          "value": "{colors.bondiBlue.500}",
          "type": "outlineColor"
        }
      },
      "border": {
        "default": {
          "value": "{colors.tangaroa.500}",
          "type": "color"
        },
        "variant": {
          "value": "{colors.tangaroa.500}",
          "type": "color"
        }
      },
      "boundary": {
        "value": "{colors.silver.500}",
        "type": "color"
      },
      "partition": {
        "value": "{colors.silverGallery.500}",
        "type": "color"
      },
      "separator": {
        "value": "{colors.tundora.200}",
        "type": "color"
      },
      "divider": {
        "value": "{colors.tundora.200}",
        "type": "color"
      },
      "fence": {
        "value": "{colors.tundora.200}",
        "type": "color"
      },
      "line": {
        "value": "{colors.tundora.200}",
        "type": "color"
      },
      "muted": {
        "value": "{colors.silverWildSand.500}",
        "type": "color"
      },
      "subtle": {
        "value": "{colors.silverGallery.500}",
        "type": "color"
      },
      "accent": {
        "default": {
          "value": "{colors.tangaroa.500}",
          "type": "color"
        },
        "onAccent": {
          "value": "{colors.tangaroa.500}",
          "type": "color"
        }
      },
      "typography": {
        "siteTitle": {
          "default": {
            "value": "{colors.tangaroa.500}",
            "type": "color"
          },
          "lighter": {
            "value": "{colors.tangaroa.500}",
            "type": "color"
          }
        },
        "heading": {
          "default": {
            "value": "{colors.tangaroa.500}",
            "type": "color"
          },
          "lighter": {
            "value": "{colors.tangaroa.500}",
            "type": "color"
          }
        },
        "body": {
          "default": {
            "value": "{colors.tundora.500}",
            "type": "color"
          },
          "lighter": {
            "value": "{colors.tangaroa.500}",
            "type": "color"
          }
        }
      },
      "action": {
        "button": {
          "primary": {
            "default": {
              "background": {
                "value": "{colors.tangaroa.500}",
                "type": "color"
              },
              "text": {
                "value": "{colors.tangaroa.500}",
                "type": "color"
              },
              "textDecoration": {
                "value": "{textDecorations.none.default}",
                "type": "textDecoration"
              },
              "border": {
                "value": "{colors.tangaroa.500}",
                "type": "color"
              }
            },
            "active": {
              "background": {
                "value": "{colors.tangaroa.500}",
                "type": "color"
              },
              "text": {
                "value": "{colors.tangaroa.500}",
                "type": "color"
              },
              "textDecoration": {
                "value": "{textDecorations.none.default}",
                "type": "textDecoration"
              },
              "border": {
                "value": "{colors.tangaroa.500}",
                "type": "color"
              }
            },
            "hover": {
              "background": {
                "value": "{colors.tangaroa.500}",
                "type": "color"
              },
              "text": {
                "value": "{colors.tangaroa.500}",
                "type": "color"
              },
              "textDecoration": {
                "value": "{textDecorations.none.default}",
                "type": "textDecoration"
              },
              "border": {
                "value": "{colors.tangaroa.500}",
                "type": "color"
              }
            }
          },
          "secondary": {
            "default": {
              "background": {
                "value": "{colors.tangaroa.500}",
                "type": "color"
              },
              "text": {
                "value": "{colors.tangaroa.500}",
                "type": "color"
              },
              "textDecoration": {
                "value": "{textDecorations.none.default}",
                "type": "textDecoration"
              },
              "border": {
                "value": "{colors.tangaroa.500}",
                "type": "color"
              }
            },
            "active": {
              "background": {
                "value": "{colors.tangaroa.500}",
                "type": "color"
              },
              "text": {
                "value": "{colors.tangaroa.500}",
                "type": "color"
              },
              "textDecoration": {
                "value": "{textDecorations.none.default}",
                "type": "textDecoration"
              },
              "border": {
                "value": "{colors.tangaroa.500}",
                "type": "color"
              }
            },
            "hover": {
              "background": {
                "value": "{colors.tangaroa.500}",
                "type": "color"
              },
              "text": {
                "value": "{colors.tangaroa.500}",
                "type": "color"
              },
              "textDecoration": {
                "value": "{textDecorations.none.default}",
                "type": "textDecoration"
              },
              "border": {
                "value": "{colors.tangaroa.500}",
                "type": "color"
              }
            }
          },
          "tertiary": {
            "default": {
              "background": {
                "value": "{colors.tangaroa.500}",
                "type": "color"
              },
              "text": {
                "value": "{colors.tangaroa.500}",
                "type": "color"
              },
              "textDecoration": {
                "value": "{textDecorations.none.default}",
                "type": "textDecoration"
              },
              "border": {
                "value": "{colors.tangaroa.500}",
                "type": "color"
              }
            },
            "active": {
              "background": {
                "value": "{colors.tangaroa.500}",
                "type": "color"
              },
              "text": {
                "value": "{colors.tangaroa.500}",
                "type": "color"
              },
              "textDecoration": {
                "value": "{textDecorations.none.default}",
                "type": "textDecoration"
              },
              "border": {
                "value": "{colors.tangaroa.500}",
                "type": "color"
              }
            },
            "hover": {
              "background": {
                "value": "{colors.tangaroa.500}",
                "type": "color"
              },
              "text": {
                "value": "{colors.tangaroa.500}",
                "type": "color"
              },
              "textDecoration": {
                "value": "{textDecorations.none.default}",
                "type": "textDecoration"
              },
              "border": {
                "value": "{colors.tangaroa.500}",
                "type": "color"
              }
            }
          }
        },
        "link": {
          "text": {
            "value": "{colors.victoriaBlue.500}",
            "type": "color"
          },
          "hover": {
            "value": "{colors.tangaroa.500}",
            "type": "color"
          },
          "active": {
            "value": "{colors.tangaroa.500}",
            "type": "color"
          },
          "visited": {
            "value": "{colors.victoriaBlue.500}",
            "type": "color"
          }
        },
        "pagination": {
          "default": {
            "background": {
              "value": "{colors.tangaroa.500}",
              "type": "color"
            },
            "text": {
              "value": "{colors.tangaroa.500}",
              "type": "color"
            },
            "border": {
              "value": "{colors.tangaroa.500}",
              "type": "color"
            }
          },
          "active": {
            "background": {
              "value": "{colors.tangaroa.500}",
              "type": "color"
            },
            "text": {
              "value": "{colors.tangaroa.500}",
              "type": "color"
            },
            "border": {
              "value": "{colors.tangaroa.500}",
              "type": "color"
            }
          },
          "hover": {
            "background": {
              "value": "{colors.tangaroa.500}",
              "type": "color"
            },
            "text": {
              "value": "{colors.tangaroa.500}",
              "type": "color"
            },
            "border": {
              "value": "{colors.tangaroa.500}",
              "type": "color"
            }
          },
          "visited": {
            "background": {
              "value": "{colors.tangaroa.500}",
              "type": "color"
            },
            "text": {
              "value": "{colors.tangaroa.500}",
              "type": "color"
            },
            "border": {
              "value": "{colors.tangaroa.500}",
              "type": "color"
            }
          }
        }
      }
    }
  },
  "shadows": {
    "default": {
      "value": "{colors.gray.900}",
      "type": "color"
    }
  }
}